{
    "双腿交叉": {
        "spread_legs": "腿部展开",
        "crossed_legs": "交叉双腿",
        "legs_folded": "双腿交叉",
        "toes_up": "脚趾朝上"
    },
    "腿部姿势": {
        "leg_up": "抬腿",
        "leg_lift": "抬腿",
        "leg_focus": "腿部聚焦"
    },
    "其他": {
        "cropped_legs": "修剪腿部",
        "knee_up": "膝盖抬起",
        "legs_up": "双腿抬起",
        "legs_apart": "双腿分开",
        "knees_together_feet_apart": "双膝并拢，双脚分开",
        "legs_together": "双腿并拢",
        "m_legs": "M型腿部",
        "feet_up": "脚抬起",
        "spread_toes": "张开脚趾",
        "no_legwear": "无腿饰",
        "crossed_ankles": "交叉脚踝",
        "foot_up": "脚抬起",
        "wide_spread_legs": "双腿张开",
        "outstretched_leg": "伸展腿部",
        "v_legs": "V型腿",
        "elbows_on_knees": "肘部放在膝盖上",
        "pov_legs": "视角腿部",
        "leg_on_another's_shoulder": "腿在另一人的肩膀上",
        "thigh_peek": "腿部窥视"
    },
    "脚部": {
        "foot_focus": "脚部聚焦"
    },
    "单腿": {
        "single_bare_leg": "单侧裸腿"
    },
    "坐姿腿部": {
        "thigh_focus": "大腿聚焦"
    }
}